konlp/VERSION
konlp/__init__.py
konlp/app/__init__.py
konlp/app/api.py
konlp/ccg/__init__.py
konlp/ccg/api.py
konlp/chat/__init__.py
konlp/chunk/__init__.py
konlp/chunk/api.py
konlp/classify/__init__.py
konlp/cluster/__init__.py
konlp/cluster/api.py
konlp/corpus/__init__.py
konlp/draw/__init__.py
konlp/embedding/__init__.py
konlp/embedding/api.py
konlp/embedding/knu_word2vec/__init__.py
konlp/embedding/knu_word2vec/knu_word2vec.py
konlp/embedding/knu_word2vec/lib/my_word2vec.so
konlp/embedding/knu_word2vec/lib/my_word2vocab.so
konlp/inference/__init__.py
konlp/inference/api.py
konlp/kma/__init__.py
konlp/kma/api.py
konlp/kma/kkma/__init__.py
konlp/kma/kkma/kkma.py
konlp/kma/kkma/lib/kkma-2.0.jar
konlp/kma/klt/__init__.py
konlp/kma/klt/klt.py
konlp/kma/klt/data/hdic/KLT2000-utf8.ini
konlp/kma/klt/data/hdic/KLT2000.ini
konlp/kma/klt/data/hdic/bigram.dic
konlp/kma/klt/data/hdic/ham-asp.dic
konlp/kma/klt/data/hdic/ham-cnn.dic
konlp/kma/klt/data/hdic/ham-cnn.s3
konlp/kma/klt/data/hdic/ham-rma.dic
konlp/kma/klt/data/hdic/ham-usr.dic
konlp/kma/klt/data/hdic/hangul.dic
konlp/kma/klt/data/hdic/stopword.dic
konlp/kma/klt/lib/__init__.py
konlp/kma/klt/lib/index.cpython-35m-x86_64-linux-gnu.so
konlp/kma/klt/lib/kma.cpython-35m-x86_64-linux-gnu.so
konlp/kma/klt/lib/libindex.so.3
konlp/kma/klt2000/__init__.py
konlp/kma/klt2000/klt2000.py
konlp/kma/klt2000/klt2023.py
konlp/kma/klt2000/hdic/ham-rma.dic
konlp/kma/klt2000/hdic/ham-usr.dic
konlp/kma/klt2000/hdic/ham-usr.dic.cc
konlp/kma/klt2000/hdic/hangul.dic
konlp/kma/klt2000/hdic/stopword.dic
konlp/kma/klt2000/lib/klt2000.jar
konlp/kma/klt2000/lib/klt2023.jar
konlp/kma/klt2023/__init__.py
konlp/kma/klt2023/klt2023.py
konlp/kma/klt2023/hdic/ham-rma.dic
konlp/kma/klt2023/hdic/ham-usr.dic
konlp/kma/klt2023/hdic/ham-usr.dic.cc
konlp/kma/klt2023/hdic/hangul.dic
konlp/kma/klt2023/hdic/stopword.dic
konlp/kma/klt2023/lib/klt2023.jar
konlp/metrics/__init__.py
konlp/misc/__init__.py
konlp/misc/kconv/__init__.py
konlp/misc/kconv/kconv.py
konlp-0.0.58.dist-info/AUTHORS.md
konlp-0.0.58.dist-info/LICENSE.txt
konlp-0.0.58.dist-info/METADATA
konlp-0.0.58.dist-info/WHEEL
konlp-0.0.58.dist-info/top_level.txt
konlp-0.0.58.dist-info/RECORD
