Metadata-Version: 2.1
Name: konlp
Version: 0.0.58
Summary: Korean Natural Language Toolkit
Home-page: https://www.konltk.org
Author: Hyunyoung Lee, GyuHyeon Nam
Author-email: hyun02.engineer@gmail.com, ngh3053@gmail.com, ty3411@gmail.com
License: UNKNOWN
Keywords: NLP,KoNLTK,NLPK,koNLP,konltk,nlpk,konlp,korean natural langugae processing,natural language processing,parsing,tagging,tokenizing,morpheme anaylisis,chunk,natural language,text anayltics
Platform: UNKNOWN
Classifier: Development Status :: 3 - Alpha
Classifier: Intended Audience :: Developers
Classifier: Intended Audience :: Education
Classifier: Intended Audience :: Information Technology
Classifier: Intended Audience :: Science/Research
Classifier: Programming Language :: Python :: 3.5
Classifier: Topic :: Scientific/Engineering
Classifier: Topic :: Scientific/Engineering
Classifier: Topic :: Scientific/Engineering
Classifier: Topic :: Scientific/Engineering
Classifier: Topic :: Text Processing
Classifier: Topic :: Text Processing :: Filters
Classifier: Topic :: Text Processing :: General
Classifier: Topic :: Text Processing :: Indexing
Classifier: Topic :: Text Processing :: Linguistic
Requires-Python: >=3
License-File: LICENSE.txt
License-File: AUTHORS.md
Requires-Dist: pytest-cov (==2.4.0)
Requires-Dist: coveralls (==1.1)
Requires-Dist: jpype1 (>=1.3.0)
